tests/__init__.py
tests/test_filter.py
viet_badwords_filter/__init__.py
viet_badwords_filter/badwords_list.py
viet_badwords_filter/filter.py
viet_badwords_filter-1.0.1.dist-info/LICENSE
viet_badwords_filter-1.0.1.dist-info/METADATA
viet_badwords_filter-1.0.1.dist-info/WHEEL
viet_badwords_filter-1.0.1.dist-info/top_level.txt
viet_badwords_filter-1.0.1.dist-info/RECORD
