Metadata-Version: 2.1
Name: viet_badwords_filter
Version: 1.0.1
Summary: A library to filter Vietnamese bad words
Home-page: https://github.com/TheQuantumCrew/viet_badwords_filter_python
Author: Dinh Truong Quang
Author-email: quangdinhvh2@example.com
Classifier: Programming Language :: Python :: 3
Classifier: License :: OSI Approved :: MIT License
Classifier: Operating System :: OS Independent
Requires-Python: >=3.6
License-File: LICENSE
